<?xml version="1.0" encoding="ISO-8859-1" standalone="no"?>
		<FORMACAO-ACADEMICA-TITULACAO>
			<GRADUACAO SEQUENCIA-FORMACAO="1" NIVEL="1"
				TITULO-DO-TRABALHO-DE-CONCLUSAO-DE-CURSO="Sistema Especialista para Diagnóstico Médico"
				NOME-DO-ORIENTADOR="Marcos José Brusso" CODIGO-INSTITUICAO="087900000002"
				NOME-INSTITUICAO="Universidade de Passo Fundo" CODIGO-ORGAO=""
				NOME-ORGAO="" CODIGO-CURSO="90000001" NOME-CURSO="Ciencia da Computação"
				CODIGO-AREA-CURSO="90000001" STATUS-DO-CURSO="CONCLUIDO"
				ANO-DE-INICIO="1992" ANO-DE-CONCLUSAO="1996" FLAG-BOLSA="NAO"
				CODIGO-AGENCIA-FINANCIADORA="" NOME-AGENCIA="" NUMERO-ID-ORIENTADOR=""
				CODIGO-CURSO-CAPES=""
				TITULO-DO-TRABALHO-DE-CONCLUSAO-DE-CURSO-INGLES=""
				NOME-CURSO-INGLES="" FORMACAO-ACADEMICA-TITULACAO="" TIPO-GRADUACAO=""
				CODIGO-INSTITUICAO-GRAD="" NOME-INSTITUICAO-GRAD=""
				CODIGO-INSTITUICAO-OUTRA-GRAD="" NOME-INSTITUICAO-OUTRA-GRAD=""
				NOME-ORIENTADOR-GRAD="" />
			<MESTRADO SEQUENCIA-FORMACAO="2" NIVEL="3"
				CODIGO-INSTITUICAO="019200000005" NOME-INSTITUICAO="Universidade Federal do Rio Grande do Sul"
				CODIGO-ORGAO="" NOME-ORGAO="" CODIGO-CURSO="42000041" NOME-CURSO="Computação"
				CODIGO-AREA-CURSO="10300007" STATUS-DO-CURSO="CONCLUIDO"
				ANO-DE-INICIO="1998" ANO-DE-CONCLUSAO="2000" FLAG-BOLSA="SIM"
				CODIGO-AGENCIA-FINANCIADORA="045000000000"
				NOME-AGENCIA="Coordenação de Aperfeiçoamento de Pessoal de Nível Superior"
				ANO-DE-OBTENCAO-DO-TITULO="2000"
				TITULO-DA-DISSERTACAO-TESE="Extração de Dados Semi-estruturados com base em uma Ontologia"
				NOME-COMPLETO-DO-ORIENTADOR="Carlos Alberto Heuser" TIPO-MESTRADO=""
				NUMERO-ID-ORIENTADOR="" CODIGO-CURSO-CAPES="42001013004P4"
				TITULO-DA-DISSERTACAO-TESE-INGLES="" NOME-CURSO-INGLES="Computer Science"
				NOME-DO-CO-ORIENTADOR="" CODIGO-INSTITUICAO-DOUT=""
				NOME-INSTITUICAO-DOUT="" CODIGO-INSTITUICAO-OUTRA-DOUT=""
				NOME-INSTITUICAO-OUTRA-DOUT="" NOME-ORIENTADOR-DOUT="">
				<PALAVRAS-CHAVE PALAVRA-CHAVE-1="Dados semi-estruturados"
					PALAVRA-CHAVE-2="Banco de Dados" PALAVRA-CHAVE-3="Ontologia"
					PALAVRA-CHAVE-4="XML" PALAVRA-CHAVE-5="Documentos" PALAVRA-CHAVE-6="" />
				<AREAS-DO-CONHECIMENTO>
					<AREA-DO-CONHECIMENTO-1
						NOME-GRANDE-AREA-DO-CONHECIMENTO="CIENCIAS_EXATAS_E_DA_TERRA"
						NOME-DA-AREA-DO-CONHECIMENTO="" NOME-DA-SUB-AREA-DO-CONHECIMENTO="Sistemas de Computação"
						NOME-DA-ESPECIALIDADE="Banco de Dados" />
					<AREA-DO-CONHECIMENTO-2
						NOME-GRANDE-AREA-DO-CONHECIMENTO="CIENCIAS_EXATAS_E_DA_TERRA"
						NOME-DA-AREA-DO-CONHECIMENTO="Ciência da Computação"
						NOME-DA-SUB-AREA-DO-CONHECIMENTO="Sistemas de Computação"
						NOME-DA-ESPECIALIDADE="Documentos" />
					<AREA-DO-CONHECIMENTO-3
						NOME-GRANDE-AREA-DO-CONHECIMENTO="CIENCIAS_EXATAS_E_DA_TERRA"
						NOME-DA-AREA-DO-CONHECIMENTO="Ciência da Computação"
						NOME-DA-SUB-AREA-DO-CONHECIMENTO="Sistemas de Computação"
						NOME-DA-ESPECIALIDADE="Dados Semi Estruturados e Web" />
				</AREAS-DO-CONHECIMENTO>
				<SETORES-DE-ATIVIDADE SETOR-DE-ATIVIDADE-1="Informática"
					SETOR-DE-ATIVIDADE-2="" SETOR-DE-ATIVIDADE-3="" />
			</MESTRADO>
			<DOUTORADO SEQUENCIA-FORMACAO="3" NIVEL="4"
				CODIGO-INSTITUICAO="019200000005" NOME-INSTITUICAO="Universidade Federal do Rio Grande do Sul"
				CODIGO-ORGAO="" NOME-ORGAO="" CODIGO-CURSO="42000041" NOME-CURSO="Computação"
				CODIGO-AREA-CURSO="10300007" STATUS-DO-CURSO="CONCLUIDO"
				ANO-DE-INICIO="2000" ANO-DE-CONCLUSAO="2006" FLAG-BOLSA="SIM"
				CODIGO-AGENCIA-FINANCIADORA="045000000000"
				NOME-AGENCIA="Coordenação de Aperfeiçoamento de Pessoal de Nível Superior"
				ANO-DE-OBTENCAO-DO-TITULO="2006"
				TITULO-DA-DISSERTACAO-TESE="Uma Estratégia Genérica para Casamento Aproximado de Instâncias"
				NOME-COMPLETO-DO-ORIENTADOR="Carlos Alberto Heuser" TIPO-DOUTORADO="S"
				CODIGO-INSTITUICAO-DOUT="" NOME-INSTITUICAO-DOUT=""
				CODIGO-INSTITUICAO-OUTRA-DOUT="002200000990"
				NOME-INSTITUICAO-OUTRA-DOUT="University of Washington"
				NOME-ORIENTADOR-DOUT="Alon Halevy" NUMERO-ID-ORIENTADOR="0455487141833418"
				CODIGO-CURSO-CAPES="42001013004P4"
				TITULO-DA-DISSERTACAO-TESE-INGLES="" NOME-CURSO-INGLES="Computer Science"
				NOME-DO-ORIENTADOR-CO-TUTELA="" CODIGO-INSTITUICAO-OUTRA-CO-TUTELA=""
				CODIGO-INSTITUICAO-CO-TUTELA="" NOME-DO-ORIENTADOR-SANDUICHE=""
				CODIGO-INSTITUICAO-OUTRA-SANDUICHE="" CODIGO-INSTITUICAO-SANDUICHE=""
				NOME-DO-CO-ORIENTADOR="">
				<PALAVRAS-CHAVE PALAVRA-CHAVE-1="Casamento aproximado de dados"
					PALAVRA-CHAVE-2="Integração de Dados" PALAVRA-CHAVE-3="Funções de similaridade"
					PALAVRA-CHAVE-4="" PALAVRA-CHAVE-5="" PALAVRA-CHAVE-6="" />
				<AREAS-DO-CONHECIMENTO>
					<AREA-DO-CONHECIMENTO-1
						NOME-GRANDE-AREA-DO-CONHECIMENTO="CIENCIAS_EXATAS_E_DA_TERRA"
						NOME-DA-AREA-DO-CONHECIMENTO="" NOME-DA-SUB-AREA-DO-CONHECIMENTO="Sistemas de Computação"
						NOME-DA-ESPECIALIDADE="Banco de Dados" />
					<AREA-DO-CONHECIMENTO-2
						NOME-GRANDE-AREA-DO-CONHECIMENTO="CIENCIAS_EXATAS_E_DA_TERRA"
						NOME-DA-AREA-DO-CONHECIMENTO="Ciência da Computação"
						NOME-DA-SUB-AREA-DO-CONHECIMENTO="Sistemas de Computação"
						NOME-DA-ESPECIALIDADE="Dados Semi Estruturados e Web" />
				</AREAS-DO-CONHECIMENTO>
				<SETORES-DE-ATIVIDADE SETOR-DE-ATIVIDADE-1="Informática"
					SETOR-DE-ATIVIDADE-2="" SETOR-DE-ATIVIDADE-3="" />
			</DOUTORADO>
		</FORMACAO-ACADEMICA-TITULACAO>